xconn/__init__.py
xconn/acceptor.py
xconn/app.py
xconn/async_client.py
xconn/async_session.py
xconn/client.py
xconn/exception.py
xconn/helpers.py
xconn/joiner.py
xconn/parser.py
xconn/realm.py
xconn/router.py
xconn/server.py
xconn/session.py
xconn/transports.py
xconn/types.py
xconn/uris.py
xconn/utils.py
xconn/_client/__init__.py
xconn/_client/__main__.py
xconn/_client/async_.py
xconn/_client/cli.py
xconn/_client/helpers.py
xconn/_client/sync.py
xconn/_client/types.py
xconn/_client/watcher.py
xconn-0.5.1.dist-info/licenses/LICENSE
xconn-0.5.1.dist-info/METADATA
xconn-0.5.1.dist-info/WHEEL
xconn-0.5.1.dist-info/entry_points.txt
xconn-0.5.1.dist-info/top_level.txt
xconn-0.5.1.dist-info/RECORD
