Metadata-Version: 2.4
Name: xconn
Version: 0.5.1
Summary: https://github.com/xconnio/xconn-python
Author-email: Omer Akram <omer@xconn.io>, Mahad Munir <mahad@xconn.io>
Project-URL: Homepage, https://github.com/xconnio/xconn-python
Project-URL: Bug Tracker, https://github.com/xconnio/xconn-python/issues
Classifier: Development Status :: 4 - Beta
Classifier: Programming Language :: Python :: 3.10
Classifier: Programming Language :: Python :: 3.11
Classifier: Programming Language :: Python :: 3.12
Classifier: Programming Language :: Python :: 3.13
Requires-Python: >=3.10
License-File: LICENSE
Requires-Dist: websockets
Requires-Dist: wampproto>=0.4.0
Requires-Dist: aiohttp
Requires-Dist: uvloop
Requires-Dist: pydantic
Requires-Dist: pyyaml
Requires-Dist: python-dotenv
Requires-Dist: watchdog
Provides-Extra: test
Requires-Dist: coverage; extra == "test"
Requires-Dist: pytest; extra == "test"
Requires-Dist: pytest-asyncio; extra == "test"
Requires-Dist: ruff; extra == "test"
Requires-Dist: pytest-timeout; extra == "test"
Provides-Extra: publish
Requires-Dist: twine; extra == "publish"
Requires-Dist: build; extra == "publish"
Provides-Extra: dev
Requires-Dist: mkdocs-material[imaging]; extra == "dev"
Requires-Dist: wampproto; extra == "dev"
Provides-Extra: capnproto
Requires-Dist: wampproto-capnproto; extra == "capnproto"
Dynamic: license-file
